{"cameraMode":{"drawMode":0,"name":"Shaded","section":"Shading Mode"},"sceneLighting":false,"audioPlay":false,"sceneViewState":{"m_AlwaysRefresh":false,"showFog":false,"showSkybox":false,"showFlares":false,"showImageEffects":false,"showParticleSystems":false,"showVisualEffectGraphs":true,"m_FxEnabled":true},"in2DMode":false,"pivot":{"x":-0.15813633799552918,"y":-1.0436146259307862,"z":-0.13116170465946198},"rotation":{"x":-0.04569706693291664,"y":-0.9373288750648499,"z":0.3141597509384155,"w":-0.14800061285495759},"size":1.307286024093628,"orthographic":false}